{
  "bindings": [
    {
      "authLevel": "function",
      "type": "httpTrigger",
      "direction": "in",
      "name": "req",
      "methods": [
        "post"
      ]
    },
    {
      "type": "http",
      "direction": "out",
      "name": "res"
    },
    {
      "name": "tarefaDocument",
      "databaseName": "tarefaDatabase",
      "collectionName": "tarefaCollection",
      "createIfNotExists": true,
      "connectionStringSetting": "csantosdb_DOCUMENTDB",
      "direction": "out",
      "type": "cosmosDB"
    }
  ]
}